ovos_lang_parser/__init__.py
ovos_lang_parser/version.py
ovos_lang_parser/res/ca/langs.json
ovos_lang_parser/res/da/langs.json
ovos_lang_parser/res/de/langs.json
ovos_lang_parser/res/en/langs.json
ovos_lang_parser/res/es/langs.json
ovos_lang_parser/res/eu/langs.json
ovos_lang_parser/res/fr/langs.json
ovos_lang_parser/res/gl/langs.json
ovos_lang_parser/res/it/langs.json
ovos_lang_parser/res/nl/langs.json
ovos_lang_parser/res/pt/langs.json
ovos_lang_parser-0.0.2.dist-info/LICENSE
ovos_lang_parser-0.0.2.dist-info/METADATA
ovos_lang_parser-0.0.2.dist-info/WHEEL
ovos_lang_parser-0.0.2.dist-info/top_level.txt
ovos_lang_parser-0.0.2.dist-info/RECORD
