Metadata-Version: 2.1
Name: ovos-lang-parser
Version: 0.0.2
Summary: OpenVoiceOS's multilingual language parsing and formatting library
Home-page: https://github.com/OpenVoiceOS/ovos-lang-parser
Author: JarbasAI
Author-email: jarbasai@mailfence.com
License: Apache2.0
Classifier: Development Status :: 4 - Beta
Classifier: Intended Audience :: Developers
Classifier: Topic :: Text Processing :: Linguistic
Classifier: License :: OSI Approved :: Apache Software License
Classifier: Programming Language :: Python :: 3.6
Classifier: Programming Language :: Python :: 3.7
Classifier: Programming Language :: Python :: 3.8
Classifier: Programming Language :: Python :: 3.9
License-File: LICENSE
Requires-Dist: ovos-utils[extra]
Requires-Dist: langcodes
